{
	"type_name":"CCLayer",
	"pos":{
		"x":"i0",
		"y":25
	},
	"size":{
		"height":"i115",
		"width":250
	},
	"anchor":{
		"x":1,
		"y":0
	},
	"touchEnabled":true,
	"child_list":[
		{
			"type_name":"CCNode",
			"pos":{
				"x":0,
				"y":"i0"
			},
			"size":{
				"height":32,
				"width":"100%"
			},
			"anchor":{
				"x":0,
				"y":1
			},
			"child_list":[
				{
					"type_name":"CCLayer",
					"name":"layerMoveListDialog",
					"pos":{
						"x":0,
						"y":"i0"
					},
					"size":{
						"height":32,
						"width":"100%"
					},
					"anchor":{
						"x":0,
						"y":1
					},
					"touchEnabled":true
				},
				{
					"type_name":"CCLayerColor",
					"pos":{
						"x":0,
						"y":"i0"
					},
					"size":{
						"height":32,
						"width":"100%"
					},
					"anchor":{
						"x":0,
						"y":1
					},
					"color":1973790
				},
				{
					"type_name":"CCCheckButton",
					"name":"chDialog",
					"pos":{
						"x":0,
						"y":"50%-2"
					},
					"size":{
						"height":30,
						"width":53
					},
					"anchor":{
						"x":0,
						"y":0.5
					},
					"9sprite":true,
					"capInsets":{
						"height":19,
						"width":78,
						"x":9,
						"y":8
					},
					"frame1":"editor_res/tabButton_nor.png",
					"frame2":"editor_res/tabButton_sel.png",
					"text":"界面",
					"fontSize":15,
					"textColor2":6873690,
					"swallow":false
				},
				{
					"type_name":"CCCheckButton",
					"name":"chTemplateCtrls",
					"pos":{
						"x":57,
						"y":"50%-2"
					},
					"size":{
						"height":30,
						"width":49
					},
					"anchor":{
						"x":0,
						"y":0.5
					},
					"9sprite":true,
					"capInsets":{
						"height":19,
						"width":78,
						"x":9,
						"y":8
					},
					"frame1":"editor_res/tabButton_nor.png",
					"frame2":"editor_res/tabButton_sel.png",
					"text":"模板",
					"fontSize":15,
					"textColor2":6873690,
					"swallow":false
				},
				{
					"type_name":"CCCheckButton",
					"name":"chAniTemplates",
					"pos":{
						"x":109,
						"y":"50%-2"
					},
					"size":{
						"height":30,
						"width":49
					},
					"anchor":{
						"x":0,
						"y":0.5
					},
					"9sprite":true,
					"capInsets":{
						"height":19,
						"width":78,
						"x":9,
						"y":8
					},
					"frame1":"editor_res/tabButton_nor.png",
					"frame2":"editor_res/tabButton_sel.png",
					"text":"动画",
					"fontSize":15,
					"textColor2":6873690,
					"swallow":false
				},
				{
					"type_name":"CCButton",
					"name":"btnRefreshFileList",
					"pos":{
						"x":"i16",
						"y":15
					},
					"size":{
						"height":32,
						"width":32
					},
					"anchor":{
						"x":1,
						"y":0.5
					},
					"scale":{
						"x":0.719,
						"y":0.719
					},
					"9sprite":false,
					"frame1":"editor_res/refresh.png",
					"enableText":false,
					"tips":"刷新"
				},
				{
					"type_name":"CCButton",
					"name":"btnHideListDialog",
					"pos":{
						"x":"i4",
						"y":"i17"
					},
					"size":{
						"height":32,
						"width":32
					},
					"anchor":{
						"x":1,
						"y":0.5
					},
					"scale":{
						"x":0.71899998188019,
						"y":0.71899998188019
					},
					"9sprite":false,
					"frame1":"editor_res/close_nor.png"
				}
			]
		},
		{
			"type_name":"CCLayerColor",
			"size":{
				"height":"i32",
				"width":250
			},
			"anchor":{
				"x":0,
				"y":0
			},
			"color":3355443
		},
		{
			"type_name":"CCScale9Sprite",
			"size":{
				"height":"i30",
				"width":250
			},
			"anchor":{
				"x":0,
				"y":0
			},
			"spriteFrame":{
				"path":"editor_res/tabButton_sel.png"
			}
		},
		{
			"type_name":"CCTreeView",
			"name":"listTemplate",
			"pos":{
				"x":"50%",
				"y":0
			},
			"size":{
				"height":"i32",
				"width":"100%"
			},
			"anchor":{
				"x":0.5,
				"y":0
			},
			"template":"editor/uieditor/items/uieditor_dialog_list_template"
		},
		{
			"type_name":"CCTreeView",
			"name":"listCtrlsTemplate",
			"pos":{
				"x":"50%",
				"y":0
			},
			"size":{
				"height":"i32",
				"width":"100%"
			},
			"anchor":{
				"x":0.5,
				"y":0
			},
			"template":"editor/uieditor/items/uieditor_ctrls_list_template"
		},
		{
			"type_name":"CCTreeView",
			"name":"listAniTemplate",
			"pos":{
				"x":"50%",
				"y":0
			},
			"size":{
				"height":"i32",
				"width":"100%"
			},
			"anchor":{
				"x":0.5,
				"y":0
			},
			"template":"editor/uieditor/items/uieditor_dialog_list_template"
		}
	]
}